{"version":1,"resource":"vscode-remote://wsl%2Bubuntu/home/soufian/holbertonschool-higher_level_programming/python-classes/1-square.py","entries":[{"id":"KDRl.py","timestamp":1717509961091},{"id":"ZWqu.py","timestamp":1717509976081},{"id":"R1nl.py","timestamp":1717510038251},{"id":"Jw23.py","timestamp":1717510089061},{"id":"wRKa.py","timestamp":1717510942351},{"id":"RKde.py","timestamp":1717511276241},{"id":"koBH.py","timestamp":1728224023566},{"id":"mkKd.py","timestamp":1728225975275},{"id":"v6Jq.py","timestamp":1728226000645},{"id":"mItB.py","timestamp":1728226037205},{"id":"tLH0.py","timestamp":1728226113235},{"id":"e4XC.py","timestamp":1728226145135},{"id":"xLAa.py","timestamp":1728226158975},{"id":"QPvv.py","timestamp":1728226426375},{"id":"6UIP.py","timestamp":1738622230783}]}